pycaiso/__init__.py
pycaiso/oasis.py
pycaiso-0.2.7.dist-info/LICENSE
pycaiso-0.2.7.dist-info/WHEEL
pycaiso-0.2.7.dist-info/METADATA
pycaiso-0.2.7.dist-info/RECORD
