Metadata-Version: 2.1
Name: pycaiso
Version: 0.2.7
Summary: python wrapper for CAISO Oasis API
Home-page: https://github.com/seanswe/pycaiso
Author: Sean Swe
Author-email: seanswe@gmail.com
Classifier: License :: OSI Approved :: MIT License
